Workbook

Sheet Resumen
A1: RIUL — Tarea 1.2: Diccionario de Datos y Matriz de Coherencia
A2: Modelo relacional de 50 entidades en 3FN, organizado en 6 módulos. Los conteos se calculan con fórmulas sobre las hojas de detalle.
A4: Módulo | B4: Nombre del módulo | C4: N.º de tablas | D4: N.º de campos | E4: Idea clave para sustentar
A5: A | B5: Seguridad, Cuentas y Estructura Académica | C5: =SUMPRODUCT(('Diccionario de Datos'!$A$2:$A$334=A5)/COUNTIFS('Diccionario de Datos'!$B$2:$B$334,'Diccionario de Datos'!$B$2:$B$334)) -> 10 | D5: =COUNTIF('Diccionario de Datos'!$A$2:$A$334,A5) -> 64 | E5: Responde a "¿quién eres y qué puedes hacer?". Primero se define la estructura de la universidad (sede, facultad, programa). Luego se registra a cada persona con su cuenta y contraseña, y se le asignan roles con permisos. Cada sesión queda registrada por seguridad.
A6: B | B6: Semilleros y Proyectos | C6: =SUMPRODUCT(('Diccionario de Datos'!$A$2:$A$334=A6)/COUNTIFS('Diccionario de Datos'!$B$2:$B$334,'Diccionario de Datos'!$B$2:$B$334)) -> 7 | D6: =COUNTIF('Diccionario de Datos'!$A$2:$A$334,A6) -> 49 | E6: Un semillero es un grupo de investigación con un tema y un coordinador. Sus miembros entran y salen con el tiempo, y todo cambio se guarda en un historial. Dentro del semillero se desarrollan proyectos con sus integrantes.
A7: C | B7: Convocatorias y Postulaciones | C7: =SUMPRODUCT(('Diccionario de Datos'!$A$2:$A$334=A7)/COUNTIFS('Diccionario de Datos'!$B$2:$B$334,'Diccionario de Datos'!$B$2:$B$334)) -> 7 | D7: =COUNTIF('Diccionario de Datos'!$A$2:$A$334,A7) -> 52 | E7: La universidad abre una convocatoria con fechas y etapas, y define qué documentos se exigen. Los estudiantes se postulan y adjuntan sus archivos. Cada cambio de estado de la postulación queda guardado para poder demostrar qué pasó y cuándo.
A8: D | B8: Evaluación y Jurados | C8: =SUMPRODUCT(('Diccionario de Datos'!$A$2:$A$334=A8)/COUNTIFS('Diccionario de Datos'!$B$2:$B$334,'Diccionario de Datos'!$B$2:$B$334)) -> 7 | D8: =COUNTIF('Diccionario de Datos'!$A$2:$A$334,A8) -> 38 | E8: Cada convocatoria tiene jurados asignados y una rúbrica, que es una tabla de criterios con su peso. El jurado califica cada criterio de una postulación. Así la nota final sale de reglas claras y no de la opinión suelta de alguien.
A9: E | B9: Gamificación e Insignias | C9: =SUMPRODUCT(('Diccionario de Datos'!$A$2:$A$334=A9)/COUNTIFS('Diccionario de Datos'!$B$2:$B$334,'Diccionario de Datos'!$B$2:$B$334)) -> 7 | D9: =COUNTIF('Diccionario de Datos'!$A$2:$A$334,A9) -> 45 | E9: Para motivar la participación, cada acción suma puntos. Los puntos permiten subir de nivel, ganar insignias y aparecer en un ranking. Todo punto queda registrado como un movimiento, igual que un extracto bancario, así se puede explicar de dónde salió cada total.
A10: F | B10: Productos Científicos y Soporte | C10: =SUMPRODUCT(('Diccionario de Datos'!$A$2:$A$334=A10)/COUNTIFS('Diccionario de Datos'!$B$2:$B$334,'Diccionario de Datos'!$B$2:$B$334)) -> 12 | D10: =COUNTIF('Diccionario de Datos'!$A$2:$A$334,A10) -> 85 | E10: Aquí se guarda lo que la investigación produce: artículos y ponencias, con sus autores y los eventos donde se presentan. Además, este módulo reúne los servicios de apoyo: avisos, archivos, comentarios de revisión, auditoría y configuración general.
B11: TOTAL | C11: =SUM(C5:C10) -> 50 | D11: =SUM(D5:D10) -> 333
A13: Matriz de coherencia por flujo
A14: N.º | B14: Flujo del prototipo | C14: Controles mapeados
A15: 1 | B15: Inicio de sesión y Perfil institucional | C15: =COUNTIF('Matriz de Coherencia'!$A$2:$A$110,"1. Inicio de sesión y Perfil institucional") -> 14
A16: 2 | B16: Gestión de Semilleros | C16: =COUNTIF('Matriz de Coherencia'!$A$2:$A$110,"2. Gestión de Semilleros") -> 22
A17: 3 | B17: Publicación de Convocatorias y Cronograma | C17: =COUNTIF('Matriz de Coherencia'!$A$2:$A$110,"3. Publicación de Convocatorias y Cronograma") -> 14
A18: 4 | B18: Formulario de Postulación con adjuntos en PDF | C18: =COUNTIF('Matriz de Coherencia'!$A$2:$A$110,"4. Formulario de Postulación con adjuntos en PDF") -> 15
A19: 5 | B19: Calificación de Jurados mediante Rúbricas y Criterios | C19: =COUNTIF('Matriz de Coherencia'!$A$2:$A$110,"5. Calificación de Jurados mediante Rúbricas y Criterios") -> 13
A20: 6 | B20: Vitrina de Insignias, Historial de Puntos y Ranking | C20: =COUNTIF('Matriz de Coherencia'!$A$2:$A$110,"6. Vitrina de Insignias, Historial de Puntos y Ranking") -> 14
A21: 7 | B21: Registro de Artículos y Ponencias en Eventos | C21: =COUNTIF('Matriz de Coherencia'!$A$2:$A$110,"7. Registro de Artículos y Ponencias en Eventos") -> 17
B22: TOTAL | C22: =SUM(C15:C21) -> 109
A24: Notas:
A25: • Tablas, campos, tipos, PK, FK y UK provienen del diagrama ER cargado; los NOT NULL, DEFAULT y longitudes de VARCHAR son decisiones de diseño propuestas.
A26: • Los nombres de pantallas y controles de la matriz son los habituales de cada flujo; verifícalos contra el prototipo de Figma antes de entregar.
A27: • CRUD: C = Crear, R = Leer, U = Actualizar, D = Eliminar (normalmente baja lógica mediante el campo estado).
A28: • Restricciones: PK = llave primaria, FK = llave foránea (tabla.columna destino), UK = valor único.

Sheet Diccionario de Datos
A1: Módulo | B1: Tabla | C1: Campo / Columna | D1: Tipo SQL | E1: Restricciones | F1: Propósito funcional (fácil de explicar)
A2: A | B2: sedes | C2: id_sede | D2: BIGINT | E2: PK, autoincremental | F2: Número único de cada sede de la universidad.
A3: A | B3: sedes | C3: nombre | D3: VARCHAR(120) | E3: UK, NOT NULL | F3: Nombre de la sede (por ejemplo, Barranquilla).
A4: A | B4: sedes | C4: codigo | D4: VARCHAR(20) | E4: UK, NOT NULL | F4: Código corto institucional para identificar la sede en reportes.
A5: A | B5: sedes | C5: ciudad | D5: VARCHAR(80) | E5: NOT NULL | F5: Ciudad donde funciona la sede.
A6: A | B6: sedes | C6: direccion | D6: VARCHAR(200) | E6: NULL | F6: Dirección física de la sede.
A7: A | B7: sedes | C7: estado | D7: BOOLEAN | E7: NOT NULL, DEFAULT TRUE | F7: Indica si la sede está activa. Se desactiva en lugar de borrarse.
A8: A | B8: sedes | C8: creado_en | D8: TIMESTAMP | E8: NOT NULL, DEFAULT CURRENT_TIMESTAMP | F8: Fecha en que se registró la sede.
A9: A | B9: facultades | C9: id_facultad | D9: BIGINT | E9: PK, autoincremental | F9: Número único de cada facultad.
A10: A | B10: facultades | C10: id_sede | D10: BIGINT | E10: FK -> sedes.id_sede, NOT NULL | F10: Sede a la que pertenece la facultad.
A11: A | B11: facultades | C11: nombre | D11: VARCHAR(150) | E11: NOT NULL | F11: Nombre de la facultad (por ejemplo, Ingeniería).
A12: A | B12: facultades | C12: codigo | D12: VARCHAR(20) | E12: UK, NOT NULL | F12: Código institucional de la facultad.
... A334: F | B334: configuracion_sistema | C334: actualizado_en | D334: TIMESTAMP | E334: NOT NULL | F334: Fecha del último cambio.

Sheet Matriz de Coherencia
A1: Flujo | B1: Pantalla / Vista en Figma | C1: Control / Input Visual | D1: Tabla Destino | E1: Columna Asociada | F1: Operación CRUD | G1: Justificación de negocio
A2: 1. Inicio de sesión y Perfil institucional | B2: Inicio de sesión | C2: Campo "Correo institucional" | D2: usuarios | E2: correo_institucional | F2: R | G2: Identifica a la persona que quiere entrar. Solo existen correos de la universidad.
A3: 1. Inicio de sesión y Perfil institucional | B3: Inicio de sesión | C3: Campo "Contraseña" | D3: credenciales | E3: hash_contrasena | F3: R | G3: Se compara con la contraseña cifrada. Nunca se guarda en texto plano.
A4: 1. Inicio de sesión y Perfil institucional | B4: Inicio de sesión | C4: Botón "Continuar con cuenta institucional" | D4: credenciales | E4: proveedor, identificador_externo | F4: R | G4: Permite ingresar con la cuenta de la universidad sin crear otra clave.
A5: 1. Inicio de sesión y Perfil institucional | B5: Inicio de sesión | C5: Botón "Ingresar" (al iniciar sesión correctamente) | D5: sesiones_acceso | E5: token_hash, iniciada_en, expira_en, ip_origen | F5: C | G5: Abre una sesión segura con vencimiento y deja rastro del acceso.
A6: 1. Inicio de sesión y Perfil institucional | B6: Inicio de sesión | C6: Botón "Ingresar" (al validar la clave) | D6: credenciales | E6: ultimo_acceso_en | F6: U | G6: Registra el último ingreso exitoso.
A7: 1. Inicio de sesión y Perfil institucional | B7: Cambio de contraseña | C7: Campos "Nueva contraseña" y "Confirmar" | D7: credenciales | E7: hash_contrasena, requiere_cambio_clave | F7: U | G7: Permite renovar la clave y apagar la obligación de cambiarla.
A8: 1. Inicio de sesión y Perfil institucional | B8: Menú lateral | C8: Opciones visibles según el tipo de usuario | D8: usuario_rol, rol_permiso, permisos | E8: id_rol, codigo | F8: R | G8: Cada persona solo ve las opciones que su rol permite.
A9: 1. Inicio de sesión y Perfil institucional | B9: Menú superior | C9: Botón "Cerrar sesión" | D9: sesiones_acceso | E9: revocada_en | F9: U | G9: Termina la sesión y evita que se reutilice.
A10: 1. Inicio de sesión y Perfil institucional | B10: Perfil institucional | C10: Texto "Nombres" y "Apellidos" | D10: usuarios | E10: nombres, apellidos | F10: R / U | G10: Datos básicos del perfil que la persona puede corregir.
A11: 1. Inicio de sesión y Perfil institucional | B11: Perfil institucional | C11: Texto "Código institucional" (solo lectura) | D11: usuarios | E11: codigo_institucional | F11: R | G11: Identificador oficial; no se edita porque lo asigna la universidad.
A12: 1. Inicio de sesión y Perfil institucional | B12: Perfil institucional | C12: Campo "Teléfono" | D12: usuarios | E12: telefono | F12: U | G12: Dato de contacto opcional.
... A110: 7. Registro de Artículos y Ponencias en Eventos | B110: Notificaciones | C110: Campana de avisos con indicador de no leídos | D110: notificaciones, notificacion_destinatario | E110: titulo, mensaje; leida_en, estado_entrega | F110: R / U | G110: Informa resultados y plazos; marca cada aviso como leído.
